asyncly/__init__.py
asyncly/py.typed
asyncly/client/__init__.py
asyncly/client/base.py
asyncly/client/timeout.py
asyncly/client/typing.py
asyncly/client/handlers/__init__.py
asyncly/client/handlers/base.py
asyncly/client/handlers/exceptions.py
asyncly/client/handlers/json.py
asyncly/client/handlers/msgspec.py
asyncly/client/handlers/pydantic.py
asyncly/client/metrics/__init__.py
asyncly/client/metrics/instrumentable_client.py
asyncly/client/metrics/route_resolver.py
asyncly/client/metrics/sinks/__init__.py
asyncly/client/metrics/sinks/base.py
asyncly/client/metrics/sinks/noop.py
asyncly/client/metrics/sinks/opentelemetry.py
asyncly/client/metrics/sinks/prometheus.py
asyncly/srvmocker/__init__.py
asyncly/srvmocker/constants.py
asyncly/srvmocker/handlers.py
asyncly/srvmocker/models.py
asyncly/srvmocker/service.py
asyncly/srvmocker/responses/__init__.py
asyncly/srvmocker/responses/base.py
asyncly/srvmocker/responses/content.py
asyncly/srvmocker/responses/json.py
asyncly/srvmocker/responses/msgpack.py
asyncly/srvmocker/responses/sequence.py
asyncly/srvmocker/responses/timeout.py
asyncly/srvmocker/responses/toml.py
asyncly/srvmocker/responses/yaml.py
asyncly/srvmocker/serialization/__init__.py
asyncly/srvmocker/serialization/base.py
asyncly/srvmocker/serialization/json.py
asyncly/srvmocker/serialization/msgpack.py
asyncly/srvmocker/serialization/toml.py
asyncly/srvmocker/serialization/yaml.py
asyncly-0.5.1.dist-info/METADATA
asyncly-0.5.1.dist-info/WHEEL
asyncly-0.5.1.dist-info/RECORD
