Metadata-Version: 2.4
Name: asyncly
Version: 0.5.1
Summary: Simple HTTP client and server for your integrations based on aiohttp
Project-URL: Homepage, https://github.com/andy-takker/asyncly
Project-URL: Source, https://github.com/andy-takker/asyncly
Project-URL: Bug Tracker, https://github.com/andy-takker/asyncly/issues
Author-email: Sergey Natalenko <sergey.natalenko@mail.ru>
License-Expression: MIT
Keywords: aiohttp,client,http
Classifier: Development Status :: 4 - Beta
Classifier: Framework :: AsyncIO
Classifier: Framework :: Pytest
Classifier: Framework :: aiohttp
Classifier: Intended Audience :: Developers
Classifier: Intended Audience :: Information Technology
Classifier: Intended Audience :: System Administrators
Classifier: License :: OSI Approved :: MIT License
Classifier: Operating System :: OS Independent
Classifier: Programming Language :: Python
Classifier: Programming Language :: Python :: 3
Classifier: Programming Language :: Python :: 3.10
Classifier: Programming Language :: Python :: 3.11
Classifier: Programming Language :: Python :: 3.12
Classifier: Programming Language :: Python :: 3.13
Classifier: Topic :: Internet
Classifier: Topic :: Internet :: WWW/HTTP
Classifier: Topic :: Software Development
Classifier: Topic :: Software Development :: Libraries
Classifier: Topic :: Software Development :: Libraries :: Python Modules
Requires-Python: <4,>=3.10
Requires-Dist: aiohttp<4,>=3.9.5
Provides-Extra: msgspec
Requires-Dist: msgspec<0.20,>=0.19.0; extra == 'msgspec'
Provides-Extra: opentelemetry
Requires-Dist: opentelemetry-sdk>=1.37.0; extra == 'opentelemetry'
Provides-Extra: orjson
Requires-Dist: orjson<4,>=3.10.6; extra == 'orjson'
Provides-Extra: prometheus
Requires-Dist: prometheus-client>=0.22.1; extra == 'prometheus'
Provides-Extra: pydantic
Requires-Dist: pydantic<3,>=2.8.2; extra == 'pydantic'
